{"installation_live-setup.md":"f774bf9f","encryption_index.md":"0d83a90b","installation_configure-system.md":"731cec76","post-installation_index.md":"eb17b56f","installation_index.md":"ebc54d58","installation_install-desktop.md":"5cae1fb1","installation_mount-filesystems.md":"eeb999d3","installation_install-bootloader.md":"e10e3281","index.md":"1fef8d3e","installation_partitioning-formatting.md":"83cb35b3","installation_useful-packages.md":"88bbd9a6","installation_setup-users.md":"c1e7b4af","gaming_index.md":"96a9e464","tweaks_index.md":"47fcf20a","installation_base-installation.md":"bf6dde22","installation_reboot.md":"69ee78f0"}
