{"encryption_index.md":"L9D-gSxr","gaming_index.md":"B2tUB3Rb","index.md":"D8KLKJ67","installation_base-installation.md":"DEk_hPxz","installation_configure-system.md":"DtJ5Ra8N","installation_index.md":"CEwyb1Rt","installation_install-bootloader.md":"BVQo5H12","installation_install-desktop.md":"lMIJvfTK","installation_live-setup.md":"lUVMPS4V","installation_mount-filesystems.md":"gWsbK8YS","installation_partitioning-formatting.md":"B0ftX9Jg","installation_reboot.md":"DDgNPsyy","installation_setup-users.md":"YQ_lxQQC","installation_useful-packages.md":"Dgbdpna8","post-installation_index.md":"b0BnDvmj","tweaks_index.md":"BTWfqozf"}
