{"encryption_index.md":"8f6ab935","gaming_index.md":"f9461624","index.md":"dd3c718f","installation_base-installation.md":"5fa9a2cb","installation_configure-system.md":"bb6829ae","installation_index.md":"e46c68d6","installation_install-bootloader.md":"4f8c4c58","installation_install-desktop.md":"13d0e8d0","installation_live-setup.md":"0228da3d","installation_mount-filesystems.md":"4de555af","installation_partitioning-formatting.md":"4817962e","installation_reboot.md":"36d01836","installation_setup-users.md":"5a7f0010","installation_useful-packages.md":"0753339f","post-installation_index.md":"180dce9c","tweaks_index.md":"462af1e1"}
